{"id":"6475d2c5a85f790001d14307","first_name":"Jason","last_name":"Green","name":"Jason Green","linkedin_url":"http://www.linkedin.com/in/jasonericgreen","title":"Stanford DCI Continuing Fellow 2023","email_status":"verified","photo_url":"https://media.licdn.com/dms/image/v2/D5603AQF4IY_IjU75MA/profile-displayphoto-shrink_200_200/profile-displayphoto-shrink_200_200/0/1701925562656?e=2147483647&v=beta&t=PxQiLo4bk6pBAs1hqwAgH8rHa3Q9-1xQLoTxDY9nPCY","twitter_url":null,"github_url":null,"facebook_url":null,"extrapolated_email_confidence":null,"headline":"Founder Emergence Capital and Greenbridge Foundation","email":"email_not_unlocked@domain.com","organization_id":"65a62a73bd41a30001b34b85","employment_history":[{"_id":"68094d6724f8f40001d03927","created_at":null,"current":true,"degree":null,"description":null,"emails":null,"end_date":null,"grade_level":null,"kind":null,"major":null,"organization_id":"65a62a73bd41a30001b34b85","organization_name":"Stanford Distinguished Careers Institute (DCI)","raw_address":null,"start_date":"2023-09-01","title":"Stanford DCI Continuing Fellow 2023","updated_at":null,"id":"68094d6724f8f40001d03927","key":"68094d6724f8f40001d03927"},{"_id":"68094d6724f8f40001d03928","created_at":null,"current":true,"degree":null,"description":null,"emails":null,"end_date":null,"grade_level":null,"kind":null,"major":null,"organization_id":"5d35a337f65125b5b38ebbc4","organization_name":"Emergence Capital","raw_address":null,"start_date":"2003-01-01","title":"Founder and General Partner","updated_at":null,"id":"68094d6724f8f40001d03928","key":"68094d6724f8f40001d03928"},{"_id":"68094d6724f8f40001d03929","created_at":null,"current":true,"degree":null,"description":null,"emails":null,"end_date":null,"grade_level":null,"kind":null,"major":null,"organization_id":"60f2e89ea607b70001bc1992","organization_name":"GREENBRIDGE FAMILY FOUNDATION","raw_address":null,"start_date":"2021-06-01","title":"Founder and President","updated_at":null,"id":"68094d6724f8f40001d03929","key":"68094d6724f8f40001d03929"},{"_id":"68094d6724f8f40001d0392a","created_at":null,"current":true,"degree":null,"description":null,"emails":null,"end_date":null,"grade_level":null,"kind":null,"major":null,"organization_id":"5e1f398497290800f320157a","organization_name":"FreeWorld","raw_address":null,"start_date":"2018-12-01","title":"Chairman and Founding Board Member","updated_at":null,"id":"68094d6724f8f40001d0392a","key":"68094d6724f8f40001d0392a"},{"_id":"68094d6724f8f40001d0392b","created_at":null,"current":true,"degree":null,"description":null,"emails":null,"end_date":null,"grade_level":null,"kind":null,"major":null,"organization_id":"612707fa7c9487000157778a","organization_name":"Ignite! Reading","raw_address":null,"start_date":"2023-01-01","title":"Board Observer","updated_at":null,"id":"68094d6724f8f40001d0392b","key":"68094d6724f8f40001d0392b"}],"state":"California","city":"Burlingame","country":"United States","organization":{"id":"65a62a73bd41a30001b34b85","name":"Stanford Distinguished Careers Institute (DCI)","linkedin_url":"http://www.linkedin.com/school/stanford-dci","linkedin_uid":"69956703","founded_year":2014,"logo_url":"https://zenprospect-production.s3.amazonaws.com/uploads/pictures/680093fca6ec2500019de1f7/picture","industry":"higher education","keywords":["purpose","community","wellness","longevity","intergenerational engagement","communities"],"estimated_num_employees":22,"industries":["higher education"],"secondary_industries":[],"snippets_loaded":true,"industry_tag_id":"5567cd4c73696453e1300000","industry_tag_hash":{"higher education":"5567cd4c73696453e1300000"},"retail_location_count":0,"raw_address":"Stanford, CA 94305, US","street_address":"","city":"Stanford","state":"California","postal_code":null,"country":"United States","owned_by_organization_id":null,"seo_description":"","short_description":null,"suborganizations":[],"num_suborganizations":0,"total_funding":null,"total_funding_printed":null,"latest_funding_round_date":null,"latest_funding_stage":null,"funding_events":[],"technology_names":[],"current_technologies":[],"org_chart_root_people_ids":[],"org_chart_sector":null,"org_chart_removed":null,"org_chart_show_department_filter":null,"employee_metrics":[{"start_date":"2023-04-01","departments":[{"functions":null,"new":0,"retained":9,"churned":0}]},{"start_date":"2023-05-01","departments":[{"functions":null,"new":0,"retained":9,"churned":0}]},{"start_date":"2023-06-01","departments":[{"functions":null,"new":0,"retained":8,"churned":1}]},{"start_date":"2023-07-01","departments":[{"functions":null,"new":0,"retained":8,"churned":0}]},{"start_date":"2023-08-01","departments":[{"functions":null,"new":2,"retained":7,"churned":1}]},{"start_date":"2023-09-01","departments":[{"functions":null,"new":6,"retained":9,"churned":0}]},{"start_date":"2023-10-01","departments":[{"functions":null,"new":0,"retained":15,"churned":0}]},{"start_date":"2023-11-01","departments":[{"functions":null,"new":0,"retained":15,"churned":0}]},{"start_date":"2023-12-01","departments":[{"functions":null,"new":0,"retained":15,"churned":0}]},{"start_date":"2024-01-01","departments":[{"functions":null,"new":0,"retained":15,"churned":0}]},{"start_date":"2024-02-01","departments":[{"functions":null,"new":0,"retained":15,"churned":0}]},{"start_date":"2024-03-01","departments":[{"functions":null,"new":0,"retained":15,"churned":0}]},{"start_date":"2024-04-01","departments":[{"functions":null,"new":0,"retained":15,"churned":0}]},{"start_date":"2024-05-01","departments":[{"functions":null,"new":0,"retained":15,"churned":0}]},{"start_date":"2024-06-01","departments":[{"functions":null,"new":0,"retained":14,"churned":1}]},{"start_date":"2024-07-01","departments":[{"functions":null,"new":0,"retained":14,"churned":0}]},{"start_date":"2024-08-01","departments":[{"functions":null,"new":0,"retained":14,"churned":0}]},{"start_date":"2024-09-01","departments":[{"functions":null,"new":7,"retained":14,"churned":0}]},{"start_date":"2024-10-01","departments":[{"functions":null,"new":0,"retained":21,"churned":0}]},{"start_date":"2024-11-01","departments":[{"functions":null,"new":0,"retained":21,"churned":0}]},{"start_date":"2024-12-01","departments":[{"functions":null,"new":0,"retained":21,"churned":0}]},{"start_date":"2025-01-01","departments":[{"functions":null,"new":0,"retained":21,"churned":0}]},{"start_date":"2025-02-01","departments":[{"functions":null,"new":0,"retained":21,"churned":0}]},{"start_date":"2025-03-01","departments":[{"functions":null,"new":0,"retained":21,"churned":0}]}]},"intent_strength":null,"show_intent":false,"email_domain_catchall":false}